camel_spitter/__init__.py
camel_spitter/apps.py
camel_spitter/db_filter.py
camel_spitter/db_handler.py
camel_spitter/models.py
camel_spitter/version.py
django_camel_spitter-0.3.2.dist-info/LICENSE
django_camel_spitter-0.3.2.dist-info/METADATA
django_camel_spitter-0.3.2.dist-info/WHEEL
django_camel_spitter-0.3.2.dist-info/top_level.txt
django_camel_spitter-0.3.2.dist-info/RECORD
