Metadata-Version: 2.1
Name: django-camel-spitter
Version: 0.3.2
Summary: A library which add DBHandler to Django logging handlers.
Home-page: https://github.com/zurek11/django-camel-spitter
Author: Adam Žúrek
Author-email: adamzurek14@gmail.com
License: MIT
Platform: UNKNOWN
Classifier: Development Status :: 4 - Beta
Classifier: Programming Language :: Python
Classifier: Programming Language :: Python :: 3.5
Classifier: Programming Language :: Python :: 3.6
Classifier: Programming Language :: Python :: 3.7
Classifier: Programming Language :: Python :: 3.8
Classifier: Programming Language :: Python :: 3 :: Only
Classifier: Programming Language :: Python :: Implementation :: PyPy
Classifier: Intended Audience :: Developers
Classifier: License :: OSI Approved :: MIT License
Classifier: Topic :: Software Development :: Libraries
Requires-Dist: Django (>=2.0)
